tencent/cloud/auth/__init__.py
tencent/cloud/auth/credentials.py
tencent/cloud/auth/helper.py
tencent_cloud_sdk_auth-0.2.2.dist-info/LICENSE
tencent_cloud_sdk_auth-0.2.2.dist-info/METADATA
tencent_cloud_sdk_auth-0.2.2.dist-info/WHEEL
tencent_cloud_sdk_auth-0.2.2.dist-info/top_level.txt
tencent_cloud_sdk_auth-0.2.2.dist-info/RECORD
