Metadata-Version: 2.1
Name: tencent-cloud-sdk-auth
Version: 0.2.2
Summary: Tencent Cloud SDK for Python components. This package implements the access credential type and signature calculation related functions for the Tencent Cloud SDK.
Home-page: https://github.com/nobody-night/tencent-cloud-sdk-python
Author: Tencent Cloud
Author-email: support@xiaoyy.org
License: MIT License
Keywords: tencent-cloud sdk-python
Platform: UNKNOWN
Classifier: Programming Language :: Python :: 3.6
Classifier: License :: OSI Approved :: MIT License
Classifier: Operating System :: OS Independent
Classifier: Development Status :: 5 - Production/Stable
Requires-Python: >=3.6
License-File: LICENSE
